wordsim/__init__.py
wordsim-0.1.2.dist-info/licenses/LICENSE
wordsim-0.1.2.dist-info/METADATA
wordsim-0.1.2.dist-info/WHEEL
wordsim-0.1.2.dist-info/top_level.txt
wordsim-0.1.2.dist-info/RECORD
